{
  "period": "2026-07",
  "generated_at": "2026-07-10T04:49:42.596425",
  "party_counts_7d": {
    "Gerindra": 18,
    "PDI-P": 41,
    "Golkar": 12,
    "NasDem": 25,
    "PKB": 15,
    "PKS": 30,
    "PAN": 5,
    "Demokrat": 5
  },
  "party_counts_30d": {
    "Gerindra": 43,
    "PDI-P": 74,
    "Golkar": 41,
    "NasDem": 35,
    "PKB": 34,
    "PKS": 42,
    "PAN": 16,
    "Demokrat": 16
  },
  "agency_counts_30d": {
    "Kementerian BUMN": 20,
    "Kementerian Perdagangan": 20,
    "Kementerian Koperasi": 20,
    "Danantara": 20,
    "BPKN": 20,
    "KPPU": 20,
    "BP Batam": 20,
    "BPK Sabang": 17,
    "Dekopin": 20,
    "Badan Pengaturan BUMN": 20
  },
  "topic_counts_30d": {
    "bumn": 67,
    "danantara": 38,
    "umkm": 6,
    "perdagangan": 14,
    "investasi": 32,
    "ekspor": 4,
    "koperasi": 64,
    "merger-akuisisi": 7,
    "kartel-monopoli": 6,
    "dividen": 1
  },
  "member_counts_30d": {
    "Andre Rosiade": 17,
    "Khilmi": 1,
    "Muhammad Husein Fadlulloh": 4,
    "Mulan Jameela": 3,
    "Kawendra Lukistian": 11,
    "Mulyadi": 7,
    "Adisatrya Suryo Sulisto": 12,
    "Mufti Anam": 10,
    "Darmadi Durianto": 10,
    "Rieke Diah Pitaloka": 20,
    "Sadarestuwati": 6,
    "Ida Nurlaela": 8,
    "Budi Sulistyono": 5,
    "Totok Hedi Santosa": 3,
    "Nurdin Halid": 8,
    "Gde Sumarjaya Linggih": 7,
    "Doni Akbar": 7,
    "Firnando Hadityo Ganinduto": 6,
    "Rizki Faisal": 8,
    "Muhammad Sarmuji": 5,
    "Rachmat Gobel": 19,
    "Asep Wahyuwijaya": 6,
    "I Nengah Senantara": 5,
    "Randi Zulmariadi": 1,
    "Rudi Hartono Bangun": 3,
    "Subardi": 1,
    "Anggia Erma Rini": 2,
    "Rivqy Abdul Halim": 19,
    "Nasim Khan": 9,
    "Ida Fauziyah": 1,
    "Imas Aan Ubudiah": 3,
    "Amin Ak.": 14,
    "Rizal Bawazier": 12,
    "Ghufran": 2,
    "Ismail": 14,
    "Eko Patrio": 9,
    "Nasril Bahar": 4,
    "Iskandar": 3,
    "Sartono": 5,
    "Herman Khaeron": 11
  },
  "early_warning_counts": {
    "Hukum/Audit": 34,
    "Kinerja BUMN": 27,
    "Koperasi/UMKM": 54,
    "Perdagangan": 30
  },
  "top_headlines": [
    {
      "title": "Video: Anggota DPR Fraksi NasDem Rachmat Gobel Meninggal Dunia - 20detik",
      "entity": "Rachmat Gobel",
      "kind": "anggota",
      "published": "Fri, 10 Jul 2026 04:46:56 GMT",
      "link": "https://20.detik.com/detikupdate/20260710-260710052/video-anggota-dpr-fraksi-nasdem-rachmat-gobel-meninggal-dunia"
    },
    {
      "title": "Kemendag Perkuat Sinergi UMKM dan Ritel Modern, 11 Jenama Lokal Jadi Mitra Metro Department Store - Kompas.com",
      "entity": "Kementerian Perdagangan",
      "kind": "lembaga",
      "published": "Fri, 10 Jul 2026 04:39:00 GMT",
      "link": "https://nasional.kompas.com/read/2026/07/10/11392051/kemendag-perkuat-sinergi-umkm-dan-ritel-modern-11-jenama-lokal-jadi-mitra"
    },
    {
      "title": "Platform E-Commerce Beralih ke Profitabilitas, Kemendag: Dinamika yang Wajar - Bisnis.com - Ekonomi",
      "entity": "Kementerian Perdagangan",
      "kind": "lembaga",
      "published": "Fri, 10 Jul 2026 04:30:27 GMT",
      "link": "https://ekonomi.bisnis.com/read/20260710/12/1987073/platform-e-commerce-beralih-ke-profitabilitas-kemendag-dinamika-yang-wajar"
    },
    {
      "title": "Guru Besar USK: Konektivitas Sabang-Andaman Buka Peluang Baru bagi Ekonomi Aceh - Waspada Aceh",
      "entity": "BPK Sabang",
      "kind": "lembaga",
      "published": "Fri, 10 Jul 2026 04:19:23 GMT",
      "link": "https://waspadaaceh.com/guru-besar-usk-konektivitas-sabang-andaman-buka-peluang-baru-bagi-ekonomi-aceh/"
    },
    {
      "title": "Eko Patrio Kenang Almarhum Rachmat Gobel Sebagai Mentor yang Baik - investor.id",
      "entity": "Eko Patrio",
      "kind": "anggota",
      "published": "Fri, 10 Jul 2026 04:09:22 GMT",
      "link": "https://investor.id/national/445998/eko-patrio-kenang-almarhum-rachmat-gobel-sebagai-mentor-yang-baik"
    },
    {
      "title": "Konektivitas Sabang-India Dinilai Bisa Hidupkan Perdagangan dan Investasi - Waspada Aceh",
      "entity": "Kementerian Perdagangan",
      "kind": "lembaga",
      "published": "Fri, 10 Jul 2026 03:54:17 GMT",
      "link": "https://waspadaaceh.com/konektivitas-sabang-india-dinilai-bisa-hidupkan-perdagangan-dan-investasi/"
    },
    {
      "title": "Konektivitas Sabang-India Dinilai Bisa Hidupkan Perdagangan dan Investasi - Waspada Aceh",
      "entity": "BPK Sabang",
      "kind": "lembaga",
      "published": "Fri, 10 Jul 2026 03:54:17 GMT",
      "link": "https://waspadaaceh.com/konektivitas-sabang-india-dinilai-bisa-hidupkan-perdagangan-dan-investasi/"
    },
    {
      "title": "Menuju Danantara 2030: Cetak Biru Transformasi BUMN sebagai Pilar Kedaulatan Ekonomi dan Mesin Pertumbuhan Indonesia - Kedai Pena",
      "entity": "Danantara",
      "kind": "lembaga",
      "published": "Fri, 10 Jul 2026 03:51:31 GMT",
      "link": "https://www.kedaipena.com/menuju-danantara-2030-cetak-biru-transformasi-bumn-sebagai-pilar-kedaulatan-ekonomi-dan-mesin-pertumbuhan-indonesia/"
    },
    {
      "title": "Rosan: Danantara Jadi Mitra Strategis yang 'Diburu' Investor Asing - MetroTVNews.com",
      "entity": "Danantara",
      "kind": "lembaga",
      "published": "Fri, 10 Jul 2026 03:45:57 GMT",
      "link": "https://www.metrotvnews.com/read/NxGCPmAE-rosan-danantara-jadi-mitra-strategis-yang-diburu-investor-asing"
    },
    {
      "title": "Rachmat Gobel Wafat, Partai NasDem Berduka Kehilangan Tokoh Restorasi Bangsa - Partai NasDem",
      "entity": "Rachmat Gobel",
      "kind": "anggota",
      "published": "Fri, 10 Jul 2026 03:11:15 GMT",
      "link": "https://partainasdem.id/2026/07/09/rachmat-gobel-wafat-partai-nasdem-berduka-kehilangan-tokoh-restorasi-bangsa/"
    },
    {
      "title": "Foto : Eko Patrio Kenang Rachmat Gobel yang Mendukungnya di DPR dan Dunia Hiburan Halaman 1 - Kompas.com",
      "entity": "Eko Patrio",
      "kind": "anggota",
      "published": "Fri, 10 Jul 2026 03:05:16 GMT",
      "link": "https://nasional.kompas.com/image/2026/07/10/09545421/eko-patrio-kenang-rachmat-gobel-yang-mendukungnya-di-dpr-dan-dunia-hiburan?page=1"
    },
    {
      "title": "Meta Gandeng Kemendag Luncurkan Small Business Growth Academy untuk 150 UMKM Indonesia - SWA.co.id",
      "entity": "Kementerian Perdagangan",
      "kind": "lembaga",
      "published": "Fri, 10 Jul 2026 03:00:00 GMT",
      "link": "https://swa.co.id/read/474769/meta-gandeng-kemendag-luncurkan-small-business-growth-academy-untuk-150-umkm-indonesia"
    },
    {
      "title": "Neraca Dagang Mei Defisit Dipicu Harga Minyak, Mendag Berharap Bulan Depan Membaik - Suara Surabaya",
      "entity": "Kementerian Perdagangan",
      "kind": "lembaga",
      "published": "Fri, 10 Jul 2026 02:59:34 GMT",
      "link": "https://www.suarasurabaya.net/ekonomibisnis/2026/neraca-dagang-mei-defisit-dipicu-harga-minyak-mendag-berharap-bulan-depan-membaik/"
    },
    {
      "title": "Kemenkop Gandeng Unpad, Generasi Muda Diajak Bangun Kewirausahaan Berbasis Koperasi - Suara Pemerintah",
      "entity": "Kementerian Koperasi",
      "kind": "lembaga",
      "published": "Fri, 10 Jul 2026 02:58:24 GMT",
      "link": "https://suarapemerintah.id/2026/07/kemenkop-gandeng-unpad-generasi-muda-diajak-bangun-kewirausahaan-berbasis-koperasi/"
    },
    {
      "title": "Eko Patrio Kenang Rachmat Gobel yang Mendukungnya di DPR dan Dunia Hiburan - Kompas.com",
      "entity": "Eko Patrio",
      "kind": "anggota",
      "published": "Fri, 10 Jul 2026 02:54:00 GMT",
      "link": "https://nasional.kompas.com/read/2026/07/10/09545421/eko-patrio-kenang-rachmat-gobel-yang-mendukungnya-di-dpr-dan-dunia-hiburan"
    }
  ]
}