{
  "period": "2026-07",
  "generated_at": "2026-07-08T21:05:08.225467",
  "party_counts_7d": {
    "Gerindra": 18,
    "PDI-P": 27,
    "Golkar": 14,
    "NasDem": 13,
    "PKB": 15,
    "PKS": 25,
    "PAN": 1,
    "Demokrat": 5
  },
  "party_counts_30d": {
    "Gerindra": 38,
    "PDI-P": 57,
    "Golkar": 38,
    "NasDem": 21,
    "PKB": 32,
    "PKS": 35,
    "PAN": 12,
    "Demokrat": 14
  },
  "agency_counts_30d": {
    "Kementerian BUMN": 20,
    "Kementerian Perdagangan": 20,
    "Kementerian Koperasi": 20,
    "Danantara": 20,
    "BPKN": 15,
    "KPPU": 20,
    "BP Batam": 20,
    "BPK Sabang": 8,
    "Dekopin": 20,
    "Badan Pengaturan BUMN": 17
  },
  "topic_counts_30d": {
    "bumn": 63,
    "danantara": 38,
    "umkm": 3,
    "ekspor": 11,
    "perdagangan": 9,
    "koperasi": 61,
    "ipo": 1,
    "investasi": 22,
    "merger-akuisisi": 7,
    "kartel-monopoli": 8,
    "dividen": 1
  },
  "member_counts_30d": {
    "Andre Rosiade": 15,
    "Khilmi": 1,
    "Muhammad Husein Fadlulloh": 4,
    "Mulan Jameela": 3,
    "Kawendra Lukistian": 11,
    "Mulyadi": 4,
    "Adisatrya Suryo Sulisto": 8,
    "Mufti Anam": 7,
    "Darmadi Durianto": 8,
    "Rieke Diah Pitaloka": 15,
    "Sadarestuwati": 5,
    "Ida Nurlaela": 8,
    "Budi Sulistyono": 4,
    "Totok Hedi Santosa": 2,
    "Nurdin Halid": 8,
    "Gde Sumarjaya Linggih": 6,
    "Doni Akbar": 7,
    "Firnando Hadityo Ganinduto": 6,
    "Rizki Faisal": 6,
    "Muhammad Sarmuji": 5,
    "Rachmat Gobel": 7,
    "Asep Wahyuwijaya": 5,
    "I Nengah Senantara": 4,
    "Randi Zulmariadi": 1,
    "Rudi Hartono Bangun": 3,
    "Subardi": 1,
    "Anggia Erma Rini": 2,
    "Rivqy Abdul Halim": 18,
    "Nasim Khan": 9,
    "Ida Fauziyah": 1,
    "Imas Aan Ubudiah": 2,
    "Amin Ak.": 10,
    "Rizal Bawazier": 11,
    "Ghufran": 2,
    "Ismail": 12,
    "Eko Patrio": 5,
    "Nasril Bahar": 4,
    "Abdul Hakim Bafagih": 1,
    "Iskandar": 2,
    "Sartono": 4,
    "Herman Khaeron": 10
  },
  "early_warning_counts": {
    "Hukum/Audit": 29,
    "Kinerja BUMN": 22,
    "Koperasi/UMKM": 56,
    "Perdagangan": 32,
    "Konflik Publik": 1
  },
  "top_headlines": [
    {
      "title": "Demokrat Minta Pembahasan Revisi UU Pemilu Segera Dimulai - publika.id",
      "entity": "Herman Khaeron",
      "kind": "anggota",
      "published": "Wed, 08 Jul 2026 18:52:00 GMT",
      "link": "https://www.publika.id/demokrat-minta-revisi-uu-pemilu"
    },
    {
      "title": "Demokrat Ingin RUU Pemilu Segera Dibahas: Supaya Ada Sosialisasi - detikNews",
      "entity": "Herman Khaeron",
      "kind": "anggota",
      "published": "Wed, 08 Jul 2026 18:41:27 GMT",
      "link": "https://news.detik.com/berita/d-8566051/demokrat-ingin-ruu-pemilu-segera-dibahas-supaya-ada-sosialisasi"
    },
    {
      "title": "Wali Kota Helldy Diusulkan Menerima Penghargaan “Tokoh Penggerak Koperasi Utama - Berita Cilegon",
      "entity": "Dekopin",
      "kind": "lembaga",
      "published": "Wed, 08 Jul 2026 17:37:27 GMT",
      "link": "https://berita.cilegon.go.id/baca/Wali-Kota-Helldy-Diusulkan-Menerima-Penghargaan-%E2%80%9CTokoh-Penggerak-Koperasi-Utama/20260709/MTEyNg%3D%3D"
    },
    {
      "title": "Dinas Koperasi dan UKM Cilegon Laporkan Rentenir Berkedok Koperasi ke Kementerian - Berita Cilegon",
      "entity": "Kementerian Koperasi",
      "kind": "lembaga",
      "published": "Wed, 08 Jul 2026 17:21:32 GMT",
      "link": "https://berita.cilegon.go.id/baca/Dinas-Koperasi-dan-UKM-Cilegon-Laporkan-Rentenir-Berkedok-Koperasi-ke-Kementerian/20260709/OTYy"
    },
    {
      "title": "Danantara Resmikan Pembangunan PSEL di Bali, Nilai Investasi Capai Rp3 Triliun - MetroTVNews.com",
      "entity": "Danantara",
      "kind": "lembaga",
      "published": "Wed, 08 Jul 2026 16:32:04 GMT",
      "link": "https://www.metrotvnews.com/play/K5nCRE80-danantara-resmikan-pembangunan-psel-di-bali-nilai-investasi-capai-rp3-triliun"
    },
    {
      "title": "Mufti Anam: Jabatan Komisaris di BUMN Bukan Hadiah Politik, Penilaian Pada Hasil Kerja - gesuri.id",
      "entity": "Mufti Anam",
      "kind": "anggota",
      "published": "Wed, 08 Jul 2026 15:00:00 GMT",
      "link": "https://www.gesuri.id/pemerintahan/mufti-anam-jabatan-komisaris-di-bumn-bukan-hadiah-politik-penilaian-pada-hasil-kerja-b2pWIZbgph"
    },
    {
      "title": "Anggota DPRA Nilai Dukungan Prabowo Buka Peluang Pengembangan Pelabuhan Sabang - ACEH BISNIS",
      "entity": "BPK Sabang",
      "kind": "lembaga",
      "published": "Wed, 08 Jul 2026 14:54:45 GMT",
      "link": "https://www.acehbisnis.com/news/anggota-dpra-nilai-dukungan-prabowo-buka-peluang-pengembangan-pelabuhan-sabang/index.html"
    },
    {
      "title": "Wagub Vasko Ingin Dekopinwil Sumbar Jadi Motor Koperasi Modern dan Berdaya Saing - Langgam.id",
      "entity": "Dekopin",
      "kind": "lembaga",
      "published": "Wed, 08 Jul 2026 14:25:30 GMT",
      "link": "https://langgam.id/wagub-vasko-ingin-dekopinwil-sumbar-jadi-motor-koperasi-modern-dan-berdaya-saing/"
    },
    {
      "title": "Kemendag Lantik Irjen Baru, Mendag Busan Tekankan Pengawasan Program Prioritas - kontan.co.id",
      "entity": "Kementerian Perdagangan",
      "kind": "lembaga",
      "published": "Wed, 08 Jul 2026 14:19:03 GMT",
      "link": "https://industri.kontan.co.id/news/kemendag-lantik-irjen-baru-mendag-busan-tekankan-pengawasan-program-prioritas"
    },
    {
      "title": "Akom VI Dorong Penerbitan Regulasi Terkait Pengelolaan Iuran PPPK - Kedai Pena",
      "entity": "Subardi",
      "kind": "anggota",
      "published": "Wed, 08 Jul 2026 13:32:52 GMT",
      "link": "https://www.kedaipena.com/akom-vi-dorong-penerbitan-regulasi-terkait-pengelolaan-iuran-pppk/"
    },
    {
      "title": "Peserta Sesko TNI Diajak Perkuat Koperasi sebagai Motor Ekonomi - Rmol.id",
      "entity": "Kementerian Koperasi",
      "kind": "lembaga",
      "published": "Wed, 08 Jul 2026 13:22:00 GMT",
      "link": "https://rmol.id/amp/2026/07/08/713756/peserta-sesko-tni-diajak-perkuat-koperasi-sebagai-motor-ekonomi-"
    },
    {
      "title": "Meta dan Kemendag Luncurkan Program Pelatihan AI untuk 150 UMKM di Indonesia - BERNAS.id",
      "entity": "Kementerian Perdagangan",
      "kind": "lembaga",
      "published": "Wed, 08 Jul 2026 13:02:25 GMT",
      "link": "https://bernas.id/nasional/news/meta-kemendag-pelatihan-ai-150-umkm-indonesia"
    },
    {
      "title": "Darmadi Durianto: Perampingan BUMN Harus Didasarkan Pada Indikator Kinerja, Bukan Jumlah Perusahaan - gesuri.id",
      "entity": "Darmadi Durianto",
      "kind": "anggota",
      "published": "Wed, 08 Jul 2026 13:00:00 GMT",
      "link": "https://www.gesuri.id/pemerintahan/darmadi-durianto-perampingan-bumn-harus-didasarkan-pada-indikator-kinerja-bukan-jumlah-perusahaan-b2pWIZbgpl"
    },
    {
      "title": "Modal Awal PFII dari Danantara, Peluang Gunakan APBN Masih Dibuka - investor.id",
      "entity": "Danantara",
      "kind": "lembaga",
      "published": "Wed, 08 Jul 2026 12:44:20 GMT",
      "link": "https://investor.id/macroeconomy/445766/modal-awal-pfii-dari-danantara-peluang-gunakan-apbn-masih-dibuka"
    },
    {
      "title": "Wagub Vasko : Pengurus baru Dekopinwil Sumbar harus jadi motor transformasi koperasi modern - ANTARA News Sumbar",
      "entity": "Dekopin",
      "kind": "lembaga",
      "published": "Wed, 08 Jul 2026 12:42:27 GMT",
      "link": "https://sumbar.antaranews.com/berita/769229/wagub-vasko-pengurus-baru-dekopinwil-sumbar-harus-jadi-motor-transformasi-koperasi-modern"
    }
  ]
}