{
  "period": "2026-07",
  "generated_at": "2026-07-12T08:14:38.263843",
  "party_counts_7d": {
    "Gerindra": 15,
    "PDI-P": 52,
    "Golkar": 7,
    "NasDem": 34,
    "PKB": 20,
    "PKS": 30,
    "PAN": 4,
    "Demokrat": 5
  },
  "party_counts_30d": {
    "Gerindra": 48,
    "PDI-P": 88,
    "Golkar": 47,
    "NasDem": 37,
    "PKB": 38,
    "PKS": 48,
    "PAN": 17,
    "Demokrat": 15
  },
  "agency_counts_30d": {
    "Kementerian BUMN": 20,
    "Kementerian Perdagangan": 20,
    "Kementerian Koperasi": 20,
    "Danantara": 20,
    "BPKN": 20,
    "KPPU": 20,
    "BP Batam": 20,
    "BPK Sabang": 17,
    "Dekopin": 20,
    "Badan Pengaturan BUMN": 20
  },
  "topic_counts_30d": {
    "bumn": 62,
    "danantara": 37,
    "perdagangan": 17,
    "umkm": 6,
    "investasi": 38,
    "ekspor": 3,
    "koperasi": 56,
    "kartel-monopoli": 5,
    "ipo": 1,
    "merger-akuisisi": 2,
    "dividen": 1,
    "impor": 1
  },
  "member_counts_30d": {
    "Andre Rosiade": 20,
    "Khilmi": 1,
    "Muhammad Husein Fadlulloh": 4,
    "Mulan Jameela": 3,
    "Kawendra Lukistian": 12,
    "Mulyadi": 8,
    "Adisatrya Suryo Sulisto": 17,
    "Mufti Anam": 11,
    "Darmadi Durianto": 16,
    "Rieke Diah Pitaloka": 20,
    "I Gusti Ngurah Kesuma Kelakan": 1,
    "Sadarestuwati": 6,
    "Ida Nurlaela": 10,
    "Budi Sulistyono": 4,
    "Totok Hedi Santosa": 3,
    "Nurdin Halid": 9,
    "Gde Sumarjaya Linggih": 7,
    "Doni Akbar": 8,
    "Firnando Hadityo Ganinduto": 7,
    "Rizki Faisal": 9,
    "Muhammad Sarmuji": 7,
    "Rachmat Gobel": 20,
    "Asep Wahyuwijaya": 5,
    "I Nengah Senantara": 4,
    "Randi Zulmariadi": 1,
    "Rudi Hartono Bangun": 3,
    "Subardi": 4,
    "Anggia Erma Rini": 3,
    "Rivqy Abdul Halim": 20,
    "Nasim Khan": 11,
    "Ida Fauziyah": 1,
    "Imas Aan Ubudiah": 3,
    "Amin Ak.": 16,
    "Rizal Bawazier": 13,
    "Ghufran": 2,
    "Ismail": 17,
    "Eko Patrio": 9,
    "Nasril Bahar": 4,
    "Iskandar": 4,
    "Sartono": 3,
    "Herman Khaeron": 12
  },
  "early_warning_counts": {
    "Hukum/Audit": 39,
    "Kinerja BUMN": 30,
    "Koperasi/UMKM": 54,
    "Perdagangan": 26
  },
  "top_headlines": [
    {
      "title": "Kementerian Koperasi Siapkan Puluhan Ribu Koperasi Merah Putih - achmadnurhidayat.id",
      "entity": "Kementerian Koperasi",
      "kind": "lembaga",
      "published": "Sun, 12 Jul 2026 08:09:24 GMT",
      "link": "https://achmadnurhidayat.id/kementerian-koperasi-siapkan-koperasi-merah-putih"
    },
    {
      "title": "Ketum Dekopin: Baru di Era Presiden Prabowo Gerakan Koperasi Dapat Perhatian - detikNews",
      "entity": "Dekopin",
      "kind": "lembaga",
      "published": "Sun, 12 Jul 2026 08:04:47 GMT",
      "link": "https://news.detik.com/berita/d-8570624/ketum-dekopin-baru-di-era-presiden-prabowo-gerakan-koperasi-dapat-perhatian"
    },
    {
      "title": "Prabowo Hadiri Puncak Hari Koperasi Nasional Ke-79 - detikNews",
      "entity": "Kementerian Koperasi",
      "kind": "lembaga",
      "published": "Sun, 12 Jul 2026 07:27:19 GMT",
      "link": "https://news.detik.com/berita/d-8570573/prabowo-hadiri-puncak-hari-koperasi-nasional-ke-79"
    },
    {
      "title": "Prabowo Hadiri Puncak Hari Koperasi Nasional Ke-79 - detikNews",
      "entity": "Dekopin",
      "kind": "lembaga",
      "published": "Sun, 12 Jul 2026 07:27:19 GMT",
      "link": "https://news.detik.com/berita/d-8570573/prabowo-hadiri-puncak-hari-koperasi-nasional-ke-79"
    },
    {
      "title": "Belajar dari Kegagalan KUD, Dosen UMM Ingatkan KDMP Harus Berbasis Pemberdayaan Desa - PWMU.CO",
      "entity": "Kementerian Koperasi",
      "kind": "lembaga",
      "published": "Sun, 12 Jul 2026 06:44:20 GMT",
      "link": "https://pwmu.co/belajar-dari-kegagalan-kud-dosen-umm-ingatkan-kdmp-harus-berbasis-pemberdayaan-desa/"
    },
    {
      "title": "Jangan Cuma Kejar Kuantitas, Sri Untari Soroti Persoalan Gerakan Koperasi Indonesia - Lentera.co",
      "entity": "Dekopin",
      "kind": "lembaga",
      "published": "Sun, 12 Jul 2026 06:19:38 GMT",
      "link": "https://lentera.co/post/item/235804/Jangan-Cuma-Kejar-Kuantitas-Sri-Untari-Soroti-Persoalan-Gerakan-Koperasi-Indonesia"
    },
    {
      "title": "KSP dan KSPPS Dominasi Aset Koperasi, Kopdes Merah Putih Masih Tahap Awal - kontan.co.id",
      "entity": "Kementerian Koperasi",
      "kind": "lembaga",
      "published": "Sun, 12 Jul 2026 05:58:11 GMT",
      "link": "https://nasional.kontan.co.id/news/ksp-dan-kspps-dominasi-aset-koperasi-kopdes-merah-putih-masih-tahap-awal"
    },
    {
      "title": "Anggota DPR RI Adisatrya Suryo Sulisto Resmikan Gedung PKK Desa Karanggintung, Perkuat Pemberdayaan Masyarakat - otoritas.co.id",
      "entity": "Adisatrya Suryo Sulisto",
      "kind": "anggota",
      "published": "Sun, 12 Jul 2026 05:27:27 GMT",
      "link": "https://otoritas.co.id/anggota-dpr-ri-adisatrya-suryo-sulisto-resmikan-gedung-pkk-desa-karanggintung-perkuat-pemberdayaan-masyarakat/"
    },
    {
      "title": "Prabowo Bakal Hadiri Acara Puncak Peringatan Hari Koperasi Nasional ke-79 - Suara Surabaya",
      "entity": "Kementerian Koperasi",
      "kind": "lembaga",
      "published": "Sun, 12 Jul 2026 05:14:37 GMT",
      "link": "https://www.suarasurabaya.net/kelanakota/2026/prabowo-bakal-hadiri-acara-puncak-peringatan-hari-koperasi-nasional-ke-79/"
    },
    {
      "title": "Prabowo Bakal Hadiri Acara Puncak Peringatan Hari Koperasi Nasional ke-79 - Suara Surabaya",
      "entity": "Dekopin",
      "kind": "lembaga",
      "published": "Sun, 12 Jul 2026 05:14:37 GMT",
      "link": "https://www.suarasurabaya.net/kelanakota/2026/prabowo-bakal-hadiri-acara-puncak-peringatan-hari-koperasi-nasional-ke-79/"
    },
    {
      "title": "Ekonom Konstitusi: Koperasi Harus Benar-benar Jadi Sokoguru Perekonomian RI - Kedai Pena",
      "entity": "Dekopin",
      "kind": "lembaga",
      "published": "Sun, 12 Jul 2026 05:11:05 GMT",
      "link": "https://www.kedaipena.com/ekonom-konstitusi-koperasi-harus-benar-benar-jadi-sokoguru-perekonomian-ri/"
    },
    {
      "title": "Tasyakuran Hari Koperasi Indonesia Ke -79 Dekopinda Kabupaten Banyuwangi - JNN.co.id",
      "entity": "Dekopin",
      "kind": "lembaga",
      "published": "Sun, 12 Jul 2026 05:11:04 GMT",
      "link": "https://jnn.co.id/2026/07/12/tasyakuran-hari-koperasi-indonesia-ke-79-dekopinda-kabupaten-banyuwangi/"
    },
    {
      "title": "OPINI: Menghidupkan Jiwa Koperasi di Desa - Bisnis.com - Ekonomi",
      "entity": "Kementerian Koperasi",
      "kind": "lembaga",
      "published": "Sun, 12 Jul 2026 05:10:46 GMT",
      "link": "https://ekonomi.bisnis.com/read/20260712/9/1987358/opini-menghidupkan-jiwa-koperasi-di-desa"
    },
    {
      "title": "Pertumbuhan Laba BUMN Jadi Sinyal Positif bagi Perekonomian Nasional - Minews ID",
      "entity": "Badan Pengaturan BUMN",
      "kind": "lembaga",
      "published": "Sun, 12 Jul 2026 05:01:50 GMT",
      "link": "https://minews.id/news/pertumbuhan-laba-bumn-jadi-sinyal-positif-bagi-perekonomian-nasional"
    },
    {
      "title": "Kemenkop Lakukan Evaluasi Tata Letak Bangunan Koperasi Desa Merah Putih Guna Optimalkan Ekonomi Warga - beritanasionalupdate.com",
      "entity": "Kementerian Koperasi",
      "kind": "lembaga",
      "published": "Sun, 12 Jul 2026 03:04:28 GMT",
      "link": "https://beritanasionalupdate.com/news/details/1422/kemenkop-lakukan-evaluasi-tata-letak-bangunan-koperasi-desa-merah-putih-guna-optimalkan-ekonomi-warga"
    }
  ]
}